copypasta/__init__.py
copypasta/cli.py
copypasta/param_parser.py
copypasta/transformers.py
copypasta-0.0.2.dist-info/DESCRIPTION.rst
copypasta-0.0.2.dist-info/METADATA
copypasta-0.0.2.dist-info/RECORD
copypasta-0.0.2.dist-info/WHEEL
copypasta-0.0.2.dist-info/entry_points.txt
copypasta-0.0.2.dist-info/metadata.json
copypasta-0.0.2.dist-info/top_level.txt
src/__init__.py
src/cli.py
src/param_parser.py
src/transformers.py
