Metadata-Version: 2.0
Name: copypasta
Version: 0.0.2
Summary: Simple scaffolding tool
Home-page: https://github.com/zweicoder/copypasta
Author: zweicoder
Author-email: zweicoder@gmail.com
License: UNKNOWN
Platform: UNKNOWN
Classifier: Programming Language :: Python :: 3
Classifier: License :: OSI Approved :: MIT License
Classifier: Operating System :: OS Independent
Requires-Dist: click
Requires-Dist: jinja2
